{
  "project": "Adresseavisen AS",
  "timestamp": "2026-02-25T00:32:18.977Z",
  "url": "https://www.adressa.no/",
  "total_violations": 10,
  "browser_used": "chromium",
  "fallback_used": false,
  "violations": [
    {
      "id": "button-name",
      "impact": "critical",
      "description": "Ensure buttons have discernible text",
      "help": "Buttons must have discernible text",
      "helpUrl": "https://dequeuniversity.com/rules/axe/4.11/button-name?application=playwright",
      "tags": [
        "cat.name-role-value",
        "wcag2a",
        "wcag412",
        "section508",
        "section508.22.a",
        "TTv5",
        "TT6.a",
        "EN-301-549",
        "EN-9.4.1.2",
        "ACT",
        "RGAAv4",
        "RGAA-11.9.1"
      ],
      "violation_count": 2,
      "nodes": [
        {
          "html": "<button class=\"button left svelte-3viewi disabled\"></button>",
          "target": [
            ".disabled"
          ],
          "failureSummary": "Fix any of the following:\n  Element does not have inner text that is visible to screen readers\n  aria-label attribute does not exist or is empty\n  aria-labelledby attribute does not exist, references elements that do not exist or references elements that are empty\n  Element has no title attribute\n  Element does not have an implicit (wrapped) <label>\n  Element does not have an explicit <label>\n  Element's default semantics were not overridden with role=\"none\" or role=\"presentation\""
        },
        {
          "html": "<button class=\"button right svelte-3viewi\"></button>",
          "target": [
            ".right"
          ],
          "failureSummary": "Fix any of the following:\n  Element does not have inner text that is visible to screen readers\n  aria-label attribute does not exist or is empty\n  aria-labelledby attribute does not exist, references elements that do not exist or references elements that are empty\n  Element has no title attribute\n  Element does not have an implicit (wrapped) <label>\n  Element does not have an explicit <label>\n  Element's default semantics were not overridden with role=\"none\" or role=\"presentation\""
        }
      ]
    },
    {
      "id": "color-contrast",
      "impact": "serious",
      "description": "Ensure the contrast between foreground and background colors meets WCAG 2 AA minimum contrast ratio thresholds",
      "help": "Elements must meet minimum color contrast ratio thresholds",
      "helpUrl": "https://dequeuniversity.com/rules/axe/4.11/color-contrast?application=playwright",
      "tags": [
        "cat.color",
        "wcag2aa",
        "wcag143",
        "TTv5",
        "TT13.c",
        "EN-301-549",
        "EN-9.1.4.3",
        "ACT",
        "RGAAv4",
        "RGAA-3.2.1"
      ],
      "violation_count": 1,
      "nodes": [
        {
          "html": "<button class=\"Abobutton removePlussForApp\">\n  BLI ABONNENT\n</button>",
          "target": [
            ".Abobutton"
          ],
          "failureSummary": "Fix any of the following:\n  Element has insufficient color contrast of 2.64 (foreground color: #ffffff, background color: #28aae2, font size: 9.6pt (12.8px), font weight: normal). Expected contrast ratio of 4.5:1"
        }
      ]
    },
    {
      "id": "frame-title",
      "impact": "serious",
      "description": "Ensure <iframe> and <frame> elements have an accessible name",
      "help": "Frames must have an accessible name",
      "helpUrl": "https://dequeuniversity.com/rules/axe/4.11/frame-title?application=playwright",
      "tags": [
        "cat.text-alternatives",
        "wcag2a",
        "wcag412",
        "section508",
        "section508.22.i",
        "TTv5",
        "TT12.d",
        "EN-301-549",
        "EN-9.4.1.2",
        "RGAAv4",
        "RGAA-2.1.1"
      ],
      "violation_count": 1,
      "nodes": [
        {
          "html": "<iframe rel=\"nofollow\" id=\"dakapo_postopbar\" name=\"0\" width=\"100%\" src=\"https://www.adressa.no/dakapo/banner/?pubname=adressa&amp;shortcode=ADR&amp;pos=topbar\" class=\"campaign\" style=\"height: 122px;\"></iframe>",
          "target": [
            "#dakapo_postopbar"
          ],
          "failureSummary": "Fix any of the following:\n  Element has no title attribute\n  aria-label attribute does not exist or is empty\n  aria-labelledby attribute does not exist, references elements that do not exist or references elements that are empty\n  Element's default semantics were not overridden with role=\"none\" or role=\"presentation\""
        }
      ]
    },
    {
      "id": "heading-order",
      "impact": "moderate",
      "description": "Ensure the order of headings is semantically correct",
      "help": "Heading levels should only increase by one",
      "helpUrl": "https://dequeuniversity.com/rules/axe/4.11/heading-order?application=playwright",
      "tags": [
        "cat.semantics",
        "best-practice"
      ],
      "violation_count": 1,
      "nodes": [
        {
          "html": "<h3 style=\"--font-size-override: 1.00;\"><!----> <span>Bodø/Glimt slo ut Inter i Milano: – Surrealistisk</span>  <!----></h3>",
          "target": [
            ".ThreeTeasers.grid:nth-child(1) > .is-section-sport-skin.life20.is-skin > a > .t100 > h3"
          ],
          "failureSummary": "Fix any of the following:\n  Heading order invalid"
        }
      ]
    },
    {
      "id": "image-alt",
      "impact": "critical",
      "description": "Ensure <img> elements have alternative text or a role of none or presentation",
      "help": "Images must have alternative text",
      "helpUrl": "https://dequeuniversity.com/rules/axe/4.11/image-alt?application=playwright",
      "tags": [
        "cat.text-alternatives",
        "wcag2a",
        "wcag111",
        "section508",
        "section508.22.a",
        "TTv5",
        "TT7.a",
        "TT7.b",
        "EN-301-549",
        "EN-9.1.1.1",
        "ACT",
        "RGAAv4",
        "RGAA-1.1.1"
      ],
      "violation_count": 24,
      "nodes": [
        {
          "html": "<img src=\"\" class=\"off\">",
          "target": [
            ".center.no-padding.table-cell:nth-child(2) > .fade-image.icon > .off[src=\"\"]"
          ],
          "failureSummary": "Fix any of the following:\n  Element does not have an alt attribute\n  aria-label attribute does not exist or is empty\n  aria-labelledby attribute does not exist, references elements that do not exist or references elements that are empty\n  Element has no title attribute\n  Element's default semantics were not overridden with role=\"none\" or role=\"presentation\""
        },
        {
          "html": "<img src=\"https://spesial.adressa.no/weather/assets/cloudy.svg\" class=\"on\">",
          "target": [
            ".center.no-padding.table-cell:nth-child(2) > .fade-image.icon > .on"
          ],
          "failureSummary": "Fix any of the following:\n  Element does not have an alt attribute\n  aria-label attribute does not exist or is empty\n  aria-labelledby attribute does not exist, references elements that do not exist or references elements that are empty\n  Element has no title attribute\n  Element's default semantics were not overridden with role=\"none\" or role=\"presentation\""
        },
        {
          "html": "<img src=\"\" class=\"off\">",
          "target": [
            ".center.no-padding.table-cell:nth-child(3) > .fade-image.icon > .off[src=\"\"]"
          ],
          "failureSummary": "Fix any of the following:\n  Element does not have an alt attribute\n  aria-label attribute does not exist or is empty\n  aria-labelledby attribute does not exist, references elements that do not exist or references elements that are empty\n  Element has no title attribute\n  Element's default semantics were not overridden with role=\"none\" or role=\"presentation\""
        },
        {
          "html": "<img src=\"https://spesial.adressa.no/weather/assets/lightsleet.svg\" class=\"on\">",
          "target": [
            ".center.no-padding.table-cell:nth-child(3) > .fade-image.icon > .on"
          ],
          "failureSummary": "Fix any of the following:\n  Element does not have an alt attribute\n  aria-label attribute does not exist or is empty\n  aria-labelledby attribute does not exist, references elements that do not exist or references elements that are empty\n  Element has no title attribute\n  Element's default semantics were not overridden with role=\"none\" or role=\"presentation\""
        },
        {
          "html": "<img src=\"\" class=\"off\">",
          "target": [
            ".center.no-padding.table-cell:nth-child(4) > .fade-image.icon > .off[src=\"\"]"
          ],
          "failureSummary": "Fix any of the following:\n  Element does not have an alt attribute\n  aria-label attribute does not exist or is empty\n  aria-labelledby attribute does not exist, references elements that do not exist or references elements that are empty\n  Element has no title attribute\n  Element's default semantics were not overridden with role=\"none\" or role=\"presentation\""
        },
        {
          "html": "<img src=\"https://spesial.adressa.no/weather/assets/sleet.svg\" class=\"on\">",
          "target": [
            ".center.no-padding.table-cell:nth-child(4) > .fade-image.icon > .on"
          ],
          "failureSummary": "Fix any of the following:\n  Element does not have an alt attribute\n  aria-label attribute does not exist or is empty\n  aria-labelledby attribute does not exist, references elements that do not exist or references elements that are empty\n  Element has no title attribute\n  Element's default semantics were not overridden with role=\"none\" or role=\"presentation\""
        },
        {
          "html": "<img src=\"\" class=\"off\">",
          "target": [
            ".center.no-padding.table-cell:nth-child(5) > .fade-image.icon > .off[src=\"\"]"
          ],
          "failureSummary": "Fix any of the following:\n  Element does not have an alt attribute\n  aria-label attribute does not exist or is empty\n  aria-labelledby attribute does not exist, references elements that do not exist or references elements that are empty\n  Element has no title attribute\n  Element's default semantics were not overridden with role=\"none\" or role=\"presentation\""
        },
        {
          "html": "<img src=\"https://spesial.adressa.no/weather/assets/heavysleet.svg\" class=\"on\">",
          "target": [
            ".center.no-padding.table-cell:nth-child(5) > .fade-image.icon > .on"
          ],
          "failureSummary": "Fix any of the following:\n  Element does not have an alt attribute\n  aria-label attribute does not exist or is empty\n  aria-labelledby attribute does not exist, references elements that do not exist or references elements that are empty\n  Element has no title attribute\n  Element's default semantics were not overridden with role=\"none\" or role=\"presentation\""
        },
        {
          "html": "<img src=\"\" class=\"off\">",
          "target": [
            ".center.no-padding.table-cell:nth-child(6) > .fade-image.icon > .off[src=\"\"]"
          ],
          "failureSummary": "Fix any of the following:\n  Element does not have an alt attribute\n  aria-label attribute does not exist or is empty\n  aria-labelledby attribute does not exist, references elements that do not exist or references elements that are empty\n  Element has no title attribute\n  Element's default semantics were not overridden with role=\"none\" or role=\"presentation\""
        },
        {
          "html": "<img src=\"https://spesial.adressa.no/weather/assets/heavysleet.svg\" class=\"on\">",
          "target": [
            ".center.no-padding.table-cell:nth-child(6) > .fade-image.icon > .on"
          ],
          "failureSummary": "Fix any of the following:\n  Element does not have an alt attribute\n  aria-label attribute does not exist or is empty\n  aria-labelledby attribute does not exist, references elements that do not exist or references elements that are empty\n  Element has no title attribute\n  Element's default semantics were not overridden with role=\"none\" or role=\"presentation\""
        },
        {
          "html": "<img src=\"\" class=\"off\">",
          "target": [
            ".center.no-padding.table-cell:nth-child(7) > .fade-image.icon > .off[src=\"\"]"
          ],
          "failureSummary": "Fix any of the following:\n  Element does not have an alt attribute\n  aria-label attribute does not exist or is empty\n  aria-labelledby attribute does not exist, references elements that do not exist or references elements that are empty\n  Element has no title attribute\n  Element's default semantics were not overridden with role=\"none\" or role=\"presentation\""
        },
        {
          "html": "<img src=\"https://spesial.adressa.no/weather/assets/lightrain.svg\" class=\"on\">",
          "target": [
            ".center.no-padding.table-cell:nth-child(7) > .fade-image.icon > .on"
          ],
          "failureSummary": "Fix any of the following:\n  Element does not have an alt attribute\n  aria-label attribute does not exist or is empty\n  aria-labelledby attribute does not exist, references elements that do not exist or references elements that are empty\n  Element has no title attribute\n  Element's default semantics were not overridden with role=\"none\" or role=\"presentation\""
        },
        {
          "html": "<img src=\"\" class=\"off\">",
          "target": [
            ".center.no-padding.table-cell:nth-child(8) > .fade-image.icon > .off[src=\"\"]"
          ],
          "failureSummary": "Fix any of the following:\n  Element does not have an alt attribute\n  aria-label attribute does not exist or is empty\n  aria-labelledby attribute does not exist, references elements that do not exist or references elements that are empty\n  Element has no title attribute\n  Element's default semantics were not overridden with role=\"none\" or role=\"presentation\""
        },
        {
          "html": "<img src=\"https://spesial.adressa.no/weather/assets/rain.svg\" class=\"on\">",
          "target": [
            ".center.no-padding.table-cell:nth-child(8) > .fade-image.icon > .on"
          ],
          "failureSummary": "Fix any of the following:\n  Element does not have an alt attribute\n  aria-label attribute does not exist or is empty\n  aria-labelledby attribute does not exist, references elements that do not exist or references elements that are empty\n  Element has no title attribute\n  Element's default semantics were not overridden with role=\"none\" or role=\"presentation\""
        },
        {
          "html": "<img src=\"\" class=\"off\">",
          "target": [
            ".center.no-padding.table-cell:nth-child(9) > .fade-image.icon > .off[src=\"\"]"
          ],
          "failureSummary": "Fix any of the following:\n  Element does not have an alt attribute\n  aria-label attribute does not exist or is empty\n  aria-labelledby attribute does not exist, references elements that do not exist or references elements that are empty\n  Element has no title attribute\n  Element's default semantics were not overridden with role=\"none\" or role=\"presentation\""
        },
        {
          "html": "<img src=\"https://spesial.adressa.no/weather/assets/rain.svg\" class=\"on\">",
          "target": [
            ".center.no-padding.table-cell:nth-child(9) > .fade-image.icon > .on"
          ],
          "failureSummary": "Fix any of the following:\n  Element does not have an alt attribute\n  aria-label attribute does not exist or is empty\n  aria-labelledby attribute does not exist, references elements that do not exist or references elements that are empty\n  Element has no title attribute\n  Element's default semantics were not overridden with role=\"none\" or role=\"presentation\""
        },
        {
          "html": "<img src=\"\" class=\"off\">",
          "target": [
            ".center.no-padding.table-cell:nth-child(10) > .fade-image.icon > .off[src=\"\"]"
          ],
          "failureSummary": "Fix any of the following:\n  Element does not have an alt attribute\n  aria-label attribute does not exist or is empty\n  aria-labelledby attribute does not exist, references elements that do not exist or references elements that are empty\n  Element has no title attribute\n  Element's default semantics were not overridden with role=\"none\" or role=\"presentation\""
        },
        {
          "html": "<img src=\"https://spesial.adressa.no/weather/assets/rain.svg\" class=\"on\">",
          "target": [
            ".center.no-padding.table-cell:nth-child(10) > .fade-image.icon > .on"
          ],
          "failureSummary": "Fix any of the following:\n  Element does not have an alt attribute\n  aria-label attribute does not exist or is empty\n  aria-labelledby attribute does not exist, references elements that do not exist or references elements that are empty\n  Element has no title attribute\n  Element's default semantics were not overridden with role=\"none\" or role=\"presentation\""
        },
        {
          "html": "<img src=\"\" class=\"off\">",
          "target": [
            ".center.no-padding.table-cell:nth-child(11) > .fade-image.icon > .off[src=\"\"]"
          ],
          "failureSummary": "Fix any of the following:\n  Element does not have an alt attribute\n  aria-label attribute does not exist or is empty\n  aria-labelledby attribute does not exist, references elements that do not exist or references elements that are empty\n  Element has no title attribute\n  Element's default semantics were not overridden with role=\"none\" or role=\"presentation\""
        },
        {
          "html": "<img src=\"https://spesial.adressa.no/weather/assets/lightrain.svg\" class=\"on\">",
          "target": [
            ".center.no-padding.table-cell:nth-child(11) > .fade-image.icon > .on"
          ],
          "failureSummary": "Fix any of the following:\n  Element does not have an alt attribute\n  aria-label attribute does not exist or is empty\n  aria-labelledby attribute does not exist, references elements that do not exist or references elements that are empty\n  Element has no title attribute\n  Element's default semantics were not overridden with role=\"none\" or role=\"presentation\""
        },
        {
          "html": "<img src=\"\" class=\"off\">",
          "target": [
            ".center.no-padding.table-cell:nth-child(12) > .fade-image.icon > .off[src=\"\"]"
          ],
          "failureSummary": "Fix any of the following:\n  Element does not have an alt attribute\n  aria-label attribute does not exist or is empty\n  aria-labelledby attribute does not exist, references elements that do not exist or references elements that are empty\n  Element has no title attribute\n  Element's default semantics were not overridden with role=\"none\" or role=\"presentation\""
        },
        {
          "html": "<img src=\"https://spesial.adressa.no/weather/assets/lightrain.svg\" class=\"on\">",
          "target": [
            ".center.no-padding.table-cell:nth-child(12) > .fade-image.icon > .on"
          ],
          "failureSummary": "Fix any of the following:\n  Element does not have an alt attribute\n  aria-label attribute does not exist or is empty\n  aria-labelledby attribute does not exist, references elements that do not exist or references elements that are empty\n  Element has no title attribute\n  Element's default semantics were not overridden with role=\"none\" or role=\"presentation\""
        },
        {
          "html": "<img src=\"\" class=\"off\">",
          "target": [
            ".center.no-padding.table-cell:nth-child(13) > .fade-image.icon > .off[src=\"\"]"
          ],
          "failureSummary": "Fix any of the following:\n  Element does not have an alt attribute\n  aria-label attribute does not exist or is empty\n  aria-labelledby attribute does not exist, references elements that do not exist or references elements that are empty\n  Element has no title attribute\n  Element's default semantics were not overridden with role=\"none\" or role=\"presentation\""
        },
        {
          "html": "<img src=\"https://spesial.adressa.no/weather/assets/cloudy.svg\" class=\"on\">",
          "target": [
            ".center.no-padding.table-cell:nth-child(13) > .fade-image.icon > .on"
          ],
          "failureSummary": "Fix any of the following:\n  Element does not have an alt attribute\n  aria-label attribute does not exist or is empty\n  aria-labelledby attribute does not exist, references elements that do not exist or references elements that are empty\n  Element has no title attribute\n  Element's default semantics were not overridden with role=\"none\" or role=\"presentation\""
        }
      ]
    },
    {
      "id": "landmark-main-is-top-level",
      "impact": "moderate",
      "description": "Ensure the main landmark is at top level",
      "help": "Main landmark should not be contained in another landmark",
      "helpUrl": "https://dequeuniversity.com/rules/axe/4.11/landmark-main-is-top-level?application=playwright",
      "tags": [
        "cat.semantics",
        "best-practice"
      ],
      "violation_count": 102,
      "nodes": [
        {
          "html": "<main class=\"text t100\"><!----> <div class=\"labels labels-top\"><span class=\"label tag RBK\">RBK</span> </div> <!----> <!----> <h3 style=\"--font-size-override: 1.00;\"><!----> <span>Trekker seg: Orker ikke mer sjikane og hets</span>  <!----></h3> <!----></main>",
          "target": [
            ".is-rbk-skin.hot70.gridspotlight > a > .t100"
          ],
          "failureSummary": "Fix any of the following:\n  The main landmark is contained in another landmark."
        },
        {
          "html": "<main class=\"text t100\"><!----> <!----> <!----> <!----> <h3 style=\"--font-size-override: 0.95;\"><!----> <span>Mannen bak noen av de største restaurant­suksessene i Trondheim er død</span>  <!----></h3> <!----></main>",
          "target": [
            ".Bundles:nth-child(1) > .OnePlusXTeasers.grid > .is-section-kultur-skin.hot70.is-skin > a > .t100"
          ],
          "failureSummary": "Fix any of the following:\n  The main landmark is contained in another landmark."
        },
        {
          "html": "<main class=\"text t100\"><!----> <!----> <!----> <!----> <h3 style=\"--font-size-override: 1.23;\"><!----> <span>«Får ikke kontakt»</span>  <!----></h3> <!----></main>",
          "target": [
            ".Bundles:nth-child(1) > .OnePlusXTeasers.grid > .hot60.gridspotlightside.life40 > a > .t100"
          ],
          "failureSummary": "Fix any of the following:\n  The main landmark is contained in another landmark."
        },
        {
          "html": "<main class=\"text t100\"><!----> <!----> <!----> <!----> <h3 style=\"--font-size-override: 1.00;\"><!----> <span>Bodø/Glimt slo ut Inter i Milano: – Surrealistisk</span>  <!----></h3> <!----></main>",
          "target": [
            ".ThreeTeasers.grid:nth-child(1) > .is-section-sport-skin.life20.is-skin > a > .t100"
          ],
          "failureSummary": "Fix any of the following:\n  The main landmark is contained in another landmark."
        },
        {
          "html": "<main class=\"text t100\"><!----> <!----> <!----> <!----> <h3 style=\"--font-size-override: 1.00;\"><!----> <span>– Det blir glatt selv om vi er ute og strør</span>  <!----></h3> <!----></main>",
          "target": [
            ".ThreeTeasers.grid:nth-child(1) > .gridtriple.hot50.life40 > a > .t100"
          ],
          "failureSummary": "Fix any of the following:\n  The main landmark is contained in another landmark."
        },
        {
          "html": "<main class=\"text t100\"><!----> <!----> <!----> <!----> <h3 style=\"--font-size-override: 1.00;\"><!----> <span>Kongen innlagt på sykehus</span>  <!----></h3> <!----></main>",
          "target": [
            ".ThreeTeasers.grid:nth-child(1) > .life20.gridtriple.hot50:nth-child(3) > a > .t100"
          ],
          "failureSummary": "Fix any of the following:\n  The main landmark is contained in another landmark."
        },
        {
          "html": "<main class=\"text t100\"><!----> <div class=\"labels labels-top\"><span class=\"label section MN24\">MN24</span> </div> <!----> <!----> <h3 style=\"--font-size-override: 1.00;\"><!----> <span>Syk­meldingene renner inn</span>  <!----></h3> <!----></main>",
          "target": [
            ".flipped.OnePlusXTeasers.grid:nth-child(4) > .is-section-mn24-skin.life20.is-skin > a > .t100"
          ],
          "failureSummary": "Fix any of the following:\n  The main landmark is contained in another landmark."
        },
        {
          "html": "<main class=\"text t100\"><!----> <!----> <!----> <!----> <h3 style=\"--font-size-override: 1.00;\"><!----> <span> – Kan bli en perle for framtida</span>  <!----></h3> <!----></main>",
          "target": [
            ".variant-a.gridspotlight.card-size-large > a > .t100"
          ],
          "failureSummary": "Fix any of the following:\n  The main landmark is contained in another landmark."
        },
        {
          "html": "<main class=\"text t100\"><!----> <!----> <!----> <!----> <h3 style=\"--font-size-override: 1.00;\"><!----> <span>Thorbjørn Jagland innlagt på sykehus</span>  <!----></h3> <!----></main>",
          "target": [
            ".flipped.OnePlusXTeasers.grid:nth-child(4) > .life20.gridspotlightside.hot50:nth-child(3) > a > .t100"
          ],
          "failureSummary": "Fix any of the following:\n  The main landmark is contained in another landmark."
        },
        {
          "html": "<main class=\"text t100\"><!----> <div class=\"labels labels-top\"><span class=\"label tag RBK\">RBK</span> </div> <!----> <!----> <h3 style=\"--font-size-override: 1.26;\"><!----> <span>Her blir han blank i øynene: - Betyr så mye</span>  <!----></h3> <!----></main>",
          "target": [
            ".gridfullsize-bundle.is-rbk-skin.card-size-large > a > .t100"
          ],
          "failureSummary": "Fix any of the following:\n  The main landmark is contained in another landmark."
        },
        {
          "html": "<main class=\"text t100\"><!----> <div class=\"labels labels-top\"><span class=\"label override RBK_-_Start_2_-_1\">RBK - Start 2 - 1</span> </div> <!----> <!----> <h3 style=\"--font-size-override: 1.30;\"><!----> <span>Danskene tok ansvar da RBK vant igjen</span>  <!----></h3> <!----></main>",
          "target": [
            ".is-rbk-skin.small-items.gridfullsize > a > .t100"
          ],
          "failureSummary": "Fix any of the following:\n  The main landmark is contained in another landmark."
        },
        {
          "html": "<main class=\"text t100\">",
          "target": [
            ".variant-a.hot70.gridspotlightside > a > .t100"
          ],
          "failureSummary": "Fix any of the following:\n  The main landmark is contained in another landmark."
        },
        {
          "html": "<main class=\"text t100\"><!----> <!----> <!----> <!----> <h3 style=\"--font-size-override: 1.00;\"><!----> <span>Rundt 300 møtte opp på Torvet: - Det er fint å være her</span>  <!----></h3> <!----></main>",
          "target": [
            ".OnePlusXTeasers.grid:nth-child(5) > .hot60.gridspotlightside.life40 > a > .t100"
          ],
          "failureSummary": "Fix any of the following:\n  The main landmark is contained in another landmark."
        },
        {
          "html": "<main class=\"text t100\">",
          "target": [
            ".ThreeTeasers.grid:nth-child(8) > .is-section-meninger-skin.opinion.hot60 > a > .t100"
          ],
          "failureSummary": "Fix any of the following:\n  The main landmark is contained in another landmark."
        },
        {
          "html": "<main class=\"text t100\"><!----> <!----> <!----> <!----> <h3 style=\"--font-size-override: 1.35;\"><!----> <span>– Det er en sinnssyk mulighet</span>  <!----></h3> <!----></main>",
          "target": [
            ".ThreeTeasers.grid:nth-child(8) > .is-section-kultur-skin.hot70.is-skin > a > .t100"
          ],
          "failureSummary": "Fix any of the following:\n  The main landmark is contained in another landmark."
        },
        {
          "html": "<main class=\"text t100\"><!----> <!----> <!----> <!----> <h3><!----> <span>Overraskende råd fra hjerne­forsker: Dette er viktigst</span>  <!----></h3> <!----></main>",
          "target": [
            ".ThreeTeasers.grid:nth-child(8) > .gridtriple.hot50.life40 > a > .t100"
          ],
          "failureSummary": "Fix any of the following:\n  The main landmark is contained in another landmark."
        },
        {
          "html": "<main class=\"text t100\"><!----> <div class=\"labels labels-top\"><span class=\"label section Adressa_debatt\">Adressa debatt</span> </div> <!----> <!----> <h3 style=\"--font-size-override: 1.00;\"><!----> <span>Svarer på kritikken: – Vanskelig å tro på</span>  <!----></h3> <!----></main>",
          "target": [
            ".flipped.OnePlusXTeasers.grid:nth-child(10) > .is-section-meninger-skin.opinion.life20 > a > .t100"
          ],
          "failureSummary": "Fix any of the following:\n  The main landmark is contained in another landmark."
        },
        {
          "html": "<main class=\"text t100\"><!----> <!----> <!----> <!----> <h3 style=\"--font-size-override: 1.30;\"><!----> <span>Kåre Opdal er død</span>  <!----></h3> <!----></main>",
          "target": [
            ".flipped.OnePlusXTeasers.grid:nth-child(10) > .is-section-kultur-skin.gridspotlight.card-size-large > a > .t100"
          ],
          "failureSummary": "Fix any of the following:\n  The main landmark is contained in another landmark."
        },
        {
          "html": "<main class=\"text t100\"><!----> <!----> <!----> <!----> <h3 style=\"--font-size-override: 1.00;\"><!----> <span>Fylkesvei var sperret i flere timer</span>  <!----></h3> <!----></main>",
          "target": [
            ".flipped.OnePlusXTeasers.grid:nth-child(10) > .life20.gridspotlightside.hot50:nth-child(3) > a > .t100"
          ],
          "failureSummary": "Fix any of the following:\n  The main landmark is contained in another landmark."
        },
        {
          "html": "<main class=\"text t100\"><!----> <!----> <!----> <!----> <h3 style=\"--font-size-override: 1.00;\"><!----> <span>Stortinget har fått nye Epstein-svar fra regjeringen</span>  <!----></h3> <!----></main>",
          "target": [
            ".ThreeTeasers.grid:nth-child(13) > .life20.gridtriple.hot50:nth-child(1) > a > .t100"
          ],
          "failureSummary": "Fix any of the following:\n  The main landmark is contained in another landmark."
        },
        {
          "html": "<main class=\"text t100\"><!----> <!----> <!----> <!----> <h3 style=\"--font-size-override: 1.00;\"><!----> <span>Sørloth-hattrick: Slo ut Brugge i mester­ligaen</span>  <!----></h3> <!----></main>",
          "target": [
            ".ThreeTeasers.grid:nth-child(13) > .is-section-sport-skin.life20.is-skin > a > .t100"
          ],
          "failureSummary": "Fix any of the following:\n  The main landmark is contained in another landmark."
        },
        {
          "html": "<main class=\"text t100\"><!----> <!----> <!----> <!----> <h3 style=\"--font-size-override: 1.00;\"><!----> <span>Kaller det et paradoks: – «Snowflake-generasjonen» stemmer ikke</span>  <!----></h3> <!----></main>",
          "target": [
            ".ThreeTeasers.grid:nth-child(13) > .hot70.gridtriple.life40 > a > .t100"
          ],
          "failureSummary": "Fix any of the following:\n  The main landmark is contained in another landmark."
        },
        {
          "html": "<main class=\"text t100\"><!----> <!----> <!----> <!----> <h3 style=\"--font-size-override: 0.95;\"><!----> <span>– Dere var noen av de første som kom oss til hjelp</span>  <!----></h3> <!----></main>",
          "target": [
            ".gridfullsize-bundle.hot70.card-size-large > a > .t100"
          ],
          "failureSummary": "Fix any of the following:\n  The main landmark is contained in another landmark."
        },
        {
          "html": "<main class=\"text t100\"><!----> <div class=\"labels labels-top\"><span class=\"label section Adressa_debatt\">Adressa debatt</span> </div> <!----> <!----> <h3 style=\"--font-size-override: 1.00;\"><!----> <span>Ikke tro at det aldri kan skje i Norge</span>  <!----></h3> <!----></main>",
          "target": [
            ".griddouble.small-items.is-section-meninger-skin > a > .t100"
          ],
          "failureSummary": "Fix any of the following:\n  The main landmark is contained in another landmark."
        },
        {
          "html": "<main class=\"text t100\"><!----> <!----> <!----> <!----> <h3 style=\"--font-size-override: 1.00;\"><!----> <span>Støre i Ukraina – gir 12 milliarder til dronekjøp</span>  <!----></h3> <!----></main>",
          "target": [
            ".griddouble.hot40.small-items > a > .t100"
          ],
          "failureSummary": "Fix any of the following:\n  The main landmark is contained in another landmark."
        },
        {
          "html": "<main class=\"text t100\"><!----> <!----> <!----> <!----> <h3 style=\"--font-size-override: 1.00;\"><!----> <span>Stenger Trondheim S i sommer</span>  <!----></h3> <!----></main>",
          "target": [
            ".OnePlusXTeasers.grid:nth-child(14) > .life20.gridspotlightside.hot50:nth-child(2) > a > .t100"
          ],
          "failureSummary": "Fix any of the following:\n  The main landmark is contained in another landmark."
        },
        {
          "html": "<main class=\"text t100\"><!----> <div class=\"labels labels-top\"><span class=\"label section Adressa_debatt\">Adressa debatt</span> </div> <!----> <!----> <h3 style=\"--font-size-override: 1.00;\"><!----> <span>Parodisk av Ap</span>  <!----></h3> <!----></main>",
          "target": [
            ".OnePlusXTeasers.grid:nth-child(14) > .is-section-meninger-skin.opinion.life20 > a > .t100"
          ],
          "failureSummary": "Fix any of the following:\n  The main landmark is contained in another landmark."
        },
        {
          "html": "<main class=\"text t100\"><!----> <div class=\"labels labels-top\"><span class=\"label section MN24\">MN24</span> </div> <!----> <!----> <h3 style=\"--font-size-override: 1.00;\"><!----> <span>Trodde de kjøpte drømme­boligen - nå tar de hus­bygger til retten</span>  <!----></h3> <!----></main>",
          "target": [
            ".flipped.OnePlusXTeasers.grid:nth-child(17) > .is-section-mn24-skin.life20.is-skin > a > .t100"
          ],
          "failureSummary": "Fix any of the following:\n  The main landmark is contained in another landmark."
        },
        {
          "html": "<main class=\"text t100\"><!----> <div class=\"labels labels-top\"><span class=\"label override trondheim\">trondheim</span> </div> <!----> <!----> <h3 style=\"--font-size-override: 1.00;\"><!----> <span>Slakter storprosjekt i Trondheim. Mener dette er mye finere</span>  <!----></h3> <!----></main>",
          "target": [
            ".flipped.OnePlusXTeasers.grid:nth-child(17) > .hot70.gridspotlight.card-size-large > a > .t100"
          ],
          "failureSummary": "Fix any of the following:\n  The main landmark is contained in another landmark."
        },
        {
          "html": "<main class=\"text t100\"><!----> <!----> <!----> <!----> <h3 style=\"--font-size-override: 1.00;\"><!----> <span>Zelenskyj viste fram bunker med kultstatus – fire år etter invasjonen</span>  <!----></h3> <!----></main>",
          "target": [
            ".flipped.OnePlusXTeasers.grid:nth-child(17) > .life20.gridspotlightside.hot50:nth-child(3) > a > .t100"
          ],
          "failureSummary": "Fix any of the following:\n  The main landmark is contained in another landmark."
        },
        {
          "html": "<main class=\"text t100\"><!----> <!----> <!----> <!----> <h3 style=\"--font-size-override: 1.00;\"><!----> <span>Bil sto i full fyr ved butikk</span>  <!----></h3> <!----></main>",
          "target": [
            ".ThreeTeasers.grid:nth-child(18) > .life20.gridtriple.hot50:nth-child(1) > a > .t100"
          ],
          "failureSummary": "Fix any of the following:\n  The main landmark is contained in another landmark."
        },
        {
          "html": "<main class=\"text t100\"><!----> <!----> <!----> <!----> <h3 style=\"--font-size-override: 1.00;\"><!----> <span>Moped­bil havnet på taket - to personer involvert</span>  <!----></h3> <!----></main>",
          "target": [
            ".ThreeTeasers.grid:nth-child(18) > .life20.gridtriple.hot50:nth-child(2) > a > .t100"
          ],
          "failureSummary": "Fix any of the following:\n  The main landmark is contained in another landmark."
        },
        {
          "html": "<main class=\"text t100\"><!----> <!----> <!----> <!----> <h3 style=\"--font-size-override: 1.00;\"><!----> <span>To barn til sykehus etter ake­ulykke - havnet under traktor</span>  <!----></h3> <!----></main>",
          "target": [
            ".ThreeTeasers.grid:nth-child(18) > .life20.gridtriple.hot50:nth-child(3) > a > .t100"
          ],
          "failureSummary": "Fix any of the following:\n  The main landmark is contained in another landmark."
        },
        {
          "html": "<main class=\"text t100\">",
          "target": [
            ".is-section-meninger-skin.opinion.hot70 > a > .t100"
          ],
          "failureSummary": "Fix any of the following:\n  The main landmark is contained in another landmark."
        },
        {
          "html": "<main class=\"text t100\"><!----> <div class=\"labels labels-top\"><span class=\"label section MN24\">MN24</span> </div> <!----> <!----> <h3 style=\"--font-size-override: 1.00;\"><!----> <span>Kommune­direktør blir festivalsjef: – Beklagelig for oss</span>  <!----></h3> <!----></main>",
          "target": [
            ".OnePlusXTeasers.grid:nth-child(20) > .is-section-mn24-skin.life20.is-skin > a > .t100"
          ],
          "failureSummary": "Fix any of the following:\n  The main landmark is contained in another landmark."
        },
        {
          "html": "<main class=\"text t100\"><!----> <!----> <!----> <!----> <h3 style=\"--font-size-override: 1.00;\"><!----> <span>Kjørte rett inn i snøfonn</span>  <!----></h3> <!----></main>",
          "target": [
            ".OnePlusXTeasers.grid:nth-child(20) > .life20.gridspotlightside.hot50:nth-child(3) > a > .t100"
          ],
          "failureSummary": "Fix any of the following:\n  The main landmark is contained in another landmark."
        },
        {
          "html": "<main class=\"text t100\"><!----> <!----> <!----> <!----> <h3 style=\"--font-size-override: 1.00;\"><!----> <span>Bekrefter innbrudd og tyveri ved NTNU</span>  <!----></h3> <!----></main>",
          "target": [
            ".OnePlusXTeasers.grid:nth-child(20) > .no-image.life20.gridspotlightside > a > .t100"
          ],
          "failureSummary": "Fix any of the following:\n  The main landmark is contained in another landmark."
        },
        {
          "html": "<main class=\"text t100\"><!----> <div class=\"labels labels-top\"><span class=\"label section Adressa_debatt\">Adressa debatt</span> </div> <!----> <!----> <h3 style=\"--font-size-override: 0.95;\"><!----> <span>– Blodbadet er meningsløst</span>  <!----></h3> <!----></main>",
          "target": [
            ".AdWithTeaser.grid:nth-child(21) > .is-section-meninger-skin.opinion.is-skin > a > .t100"
          ],
          "failureSummary": "Fix any of the following:\n  The main landmark is contained in another landmark."
        },
        {
          "html": "<main class=\"text t100\"><!----> <!----> <!----> <!----> <h3 style=\"--font-size-override: 1.10;\"><!----> <span>Advarer: – Veier kan bli stengt</span>  <!----></h3> <!----></main>",
          "target": [
            ".flipped.OnePlusXTeasers.grid:nth-child(22) > .life20.gridspotlightside.hot50:nth-child(1) > a > .t100"
          ],
          "failureSummary": "Fix any of the following:\n  The main landmark is contained in another landmark."
        },
        {
          "html": "<main class=\"text t100\"><!----> <!----> <!----> <!----> <h3 style=\"--font-size-override: 1.00;\"><!----> <span>Katja flyttet fra Russ­land til Meråker som 22-åring: – Jeg har sånn skyld­følelse for de siste fire årene</span>  <!----></h3> <!----></main>",
          "target": [
            ".flipped.OnePlusXTeasers.grid:nth-child(22) > .hot70.gridspotlight.card-size-large > a > .t100"
          ],
          "failureSummary": "Fix any of the following:\n  The main landmark is contained in another landmark."
        },
        {
          "html": "<main class=\"text t100\"><!----> <!----> <!----> <!----> <h3 style=\"--font-size-override: 1.00;\"><!----> <span>Fikk beskjed om ulykke: – Overdreven melding</span>  <!----></h3> <!----></main>",
          "target": [
            ".flipped.OnePlusXTeasers.grid:nth-child(22) > .no-image.life20.gridspotlightside > a > .t100"
          ],
          "failureSummary": "Fix any of the following:\n  The main landmark is contained in another landmark."
        },
        {
          "html": "<main class=\"text t100\"><!----> <!----> <!----> <!----> <h3 style=\"--font-size-override: 1.00;\"><!----> <span>Vondt i nakken i dag? Disse kan ha skylden</span>  <!----></h3> <!----></main>",
          "target": [
            ".flipped.OnePlusXTeasers.grid:nth-child(22) > .gridspotlightside.hot50.life40 > a > .t100"
          ],
          "failureSummary": "Fix any of the following:\n  The main landmark is contained in another landmark."
        },
        {
          "html": "<main class=\"text t100\"><!----> <!----> <!----> <!----> <h3 style=\"--font-size-override: 1.00;\"><!----> <span>Havnet i bergveggen: – Vanskelige kjøreforhold</span>  <!----></h3> <!----></main>",
          "target": [
            ".no-image.life20.gridtriple > a > .t100"
          ],
          "failureSummary": "Fix any of the following:\n  The main landmark is contained in another landmark."
        },
        {
          "html": "<main class=\"text t100\"><!----> <div class=\"labels labels-top\"><span class=\"label section MN24\">MN24</span> </div> <!----> <!----> <h3 style=\"--font-size-override: 1.00;\"><!----> <span>Trygdesvindel for millioner i Trøndelag</span>  <!----></h3> <!----></main>",
          "target": [
            ".ThreeTeasers.grid:nth-child(25) > .is-section-mn24-skin.life20.is-skin > a > .t100"
          ],
          "failureSummary": "Fix any of the following:\n  The main landmark is contained in another landmark."
        },
        {
          "html": "<main class=\"text t100\"><!----> <!----> <!----> <!----> <h3 style=\"--font-size-override: 1.10;\"><!----> <span>250 griser måtte avlives – undersøker smittefare for mennesker</span>  <!----></h3> <!----></main>",
          "target": [
            ".ThreeTeasers.grid:nth-child(25) > .hot70.gridtriple.life40 > a > .t100"
          ],
          "failureSummary": "Fix any of the following:\n  The main landmark is contained in another landmark."
        },
        {
          "html": "<main class=\"text t100\">",
          "target": [
            ".OnePlusXTeasers.grid:nth-child(26) > .is-section-meninger-skin.opinion.gridspotlight > a > .t100"
          ],
          "failureSummary": "Fix any of the following:\n  The main landmark is contained in another landmark."
        },
        {
          "html": "<main class=\"text t100\"><!----> <!----> <!----> <!----> <h3 style=\"--font-size-override: 1.00;\"><!----> <span>Væpnet politi pågrep mann med øks i boligfelt</span>  <!----></h3> <!----></main>",
          "target": [
            ".OnePlusXTeasers.grid:nth-child(26) > .life20.gridspotlightside.hot50 > a > .t100"
          ],
          "failureSummary": "Fix any of the following:\n  The main landmark is contained in another landmark."
        },
        {
          "html": "<main class=\"text t100\"><!----> <!----> <!----> <!----> <h3 style=\"--font-size-override: 1.00;\"><!----> <span>Be­krefter tuber­kulose i barne­hage i Trond­heim</span>  <!----></h3> <!----></main>",
          "target": [
            ".OnePlusXTeasers.grid:nth-child(26) > .hot60.gridspotlightside.life40 > a > .t100"
          ],
          "failureSummary": "Fix any of the following:\n  The main landmark is contained in another landmark."
        },
        {
          "html": "<main class=\"text t100\"><!----> <!----> <!----> <!----> <h3 style=\"--font-size-override: 1.15;\"><!----> <span>Tobarns­mor fortviler: – Det er eks­klud­erende</span>  <!----></h3> <!----></main>",
          "target": [
            ".hot60.gridspotlightside.life40:nth-child(1) > a > .t100"
          ],
          "failureSummary": "Fix any of the following:\n  The main landmark is contained in another landmark."
        },
        {
          "html": "<main class=\"text t100\"><!----> <!----> <!----> <!----> <h3 style=\"--font-size-override: 1.00;\"><!----> <span>– Hvis de vurderer ham som byrådsleder, er vi svært skeptiske til samarbeid</span>  <!----></h3> <!----></main>",
          "target": [
            ".flipped.OnePlusXTeasers.grid:nth-child(28) > .hot70.gridspotlight.card-size-large > a > .t100"
          ],
          "failureSummary": "Fix any of the following:\n  The main landmark is contained in another landmark."
        },
        {
          "html": "<main class=\"text t100\"><!----> <!----> <!----> <!----> <h3 style=\"--font-size-override: 1.00;\"><!----> <span>Frykter kollaps: – Vi står i en skvis</span>  <!----></h3> <!----></main>",
          "target": [
            ".flipped.OnePlusXTeasers.grid:nth-child(28) > .hot60.gridspotlightside.life40:nth-child(3) > a > .t100"
          ],
          "failureSummary": "Fix any of the following:\n  The main landmark is contained in another landmark."
        },
        {
          "html": "<main class=\"text t100\"><!----> <!----> <!----> <!----> <h3 style=\"--font-size-override: 1.00;\"><!----> <span>Sterke reaksjoner etter Teigens post om muslimer og hunder</span>  <!----></h3> <!----></main>",
          "target": [
            ".hot60.life20.gridtriple > a > .t100"
          ],
          "failureSummary": "Fix any of the following:\n  The main landmark is contained in another landmark."
        },
        {
          "html": "<main class=\"text t100\"><!----> <div class=\"labels labels-top\"><span class=\"label section Vinter-OL\">Vinter-OL</span> </div> <!----> <!----> <h3 style=\"--font-size-override: 1.15;\"><!----> <span>Sovnet fra cham­pagnen på flyet: - Jeg ble vekket på slutten</span>  <!----></h3> <!----></main>",
          "target": [
            ".ThreeTeasers.grid:nth-child(29) > .is-section-ol-skin.hot60.is-skin > a > .t100"
          ],
          "failureSummary": "Fix any of the following:\n  The main landmark is contained in another landmark."
        },
        {
          "html": "<main class=\"text t100\"><!----> <!----> <!----> <!----> <h3 style=\"--font-size-override: 1.00;\"><!----> <span>Her løper de i tunnelen i Trond­heim</span>  <!----></h3> <!----></main>",
          "target": [
            ".ThreeTeasers.grid:nth-child(29) > .gridtriple.hot50.life40 > a > .t100"
          ],
          "failureSummary": "Fix any of the following:\n  The main landmark is contained in another landmark."
        },
        {
          "html": "<main class=\"text t100\"><!----> <!----> <!----> <!----> <h3 style=\"--font-size-override: 1.20;\"><!----> <span>Familien ble enige om en endring fra nyttår: – Jeg lever mer i nuet nå</span>  <!----></h3> <!----></main>",
          "target": [
            ".AdWithTeaser.flipped.grid:nth-child(31) > .hot70.gridtriple.life40 > a > .t100"
          ],
          "failureSummary": "Fix any of the following:\n  The main landmark is contained in another landmark."
        },
        {
          "html": "<main class=\"text t100\"><!----> <!----> <!----> <!----> <h3 style=\"--font-size-override: 1.00;\"><!----> <span>Eva Joly ønsker å delta i Epstein-granskingen</span>  <!----></h3> <!----></main>",
          "target": [
            ".ThreeTeasers.grid:nth-child(32) > .life20.gridtriple.hot50 > a > .t100"
          ],
          "failureSummary": "Fix any of the following:\n  The main landmark is contained in another landmark."
        },
        {
          "html": "<main class=\"text t100\"><!----> <!----> <!----> <!----> <h3><!----> <span>Kjøpte enebolig og tok en total «make over» på under ti dager</span>  <!----></h3> <!----></main>",
          "target": [
            ".ThreeTeasers.grid:nth-child(32) > .life60.gridtriple.hot50 > a > .t100"
          ],
          "failureSummary": "Fix any of the following:\n  The main landmark is contained in another landmark."
        },
        {
          "html": "<main class=\"text t100\"><!----> <!----> <!----> <!----> <h3 style=\"--font-size-override: 1.00;\"><!----> <span>Får gave: – Nå har vi 400 millioner</span>  <!----></h3> <!----></main>",
          "target": [
            ".ThreeTeasers.grid:nth-child(32) > .hot60.gridtriple.life40 > a > .t100"
          ],
          "failureSummary": "Fix any of the following:\n  The main landmark is contained in another landmark."
        },
        {
          "html": "<main class=\"text t100\">",
          "target": [
            ".OnePlusXTeasers.grid:nth-child(35) > .is-section-meninger-skin.opinion.gridspotlight > a > .t100"
          ],
          "failureSummary": "Fix any of the following:\n  The main landmark is contained in another landmark."
        },
        {
          "html": "<main class=\"text t100\"><!----> <!----> <!----> <!----> <h3 style=\"--font-size-override: 1.00;\"><!----> <span>The Times: Tidligere USA-ambassadør Peter Mandelson pågrepet i Storbritannia</span>  <!----></h3> <!----></main>",
          "target": [
            ".OnePlusXTeasers.grid:nth-child(35) > .life20.gridspotlightside.hot50:nth-child(2) > a > .t100"
          ],
          "failureSummary": "Fix any of the following:\n  The main landmark is contained in another landmark."
        },
        {
          "html": "<main class=\"text t100\"><!----> <div class=\"labels labels-top\"><span class=\"label section Adressa_debatt\">Adressa debatt</span> </div> <!----> <!----> <h3 style=\"--font-size-override: 1.00;\"><!----> <span>Når hverdags­funksjonene flyttes ut, dør byen</span>  <!----></h3> <!----></main>",
          "target": [
            ".OnePlusXTeasers.grid:nth-child(35) > .is-section-meninger-skin.opinion.life20 > a > .t100"
          ],
          "failureSummary": "Fix any of the following:\n  The main landmark is contained in another landmark."
        },
        {
          "html": "<main class=\"text t100\"><!----> <!----> <!----> <!----> <h3 style=\"--font-size-override: 1.00;\"><!----> <span>Flere turister på norske vinterveier – slik skal sikkerheten styrkes, ifølge utvalg</span>  <!----></h3> <!----></main>",
          "target": [
            ".AdWithTeaser.grid:nth-child(36) > .life20.gridtriple.hot50 > a > .t100"
          ],
          "failureSummary": "Fix any of the following:\n  The main landmark is contained in another landmark."
        },
        {
          "html": "<main class=\"text t100\"><!----> <div class=\"labels labels-top\"><span class=\"label section MN24\">MN24</span> </div> <!----> <!----> <h3 style=\"--font-size-override: 1.00;\"><!----> <span>Uten vann i seks dager: – Låner toalettet til en ansatt</span>  <!----></h3> <!----></main>",
          "target": [
            ".flipped.OnePlusXTeasers.grid:nth-child(37) > .is-section-mn24-skin.life20.is-skin > a > .t100"
          ],
          "failureSummary": "Fix any of the following:\n  The main landmark is contained in another landmark."
        },
        {
          "html": "<main class=\"text t100\"><!----> <!----> <!----> <!----> <h3 style=\"--font-size-override: 1.00;\"><!----> <span>– Jeg skjønte tidlig at vi var litt rare</span>  <!----></h3> <!----></main>",
          "target": [
            ".flipped.OnePlusXTeasers.grid:nth-child(37) > .hot70.gridspotlight.card-size-large > a > .t100"
          ],
          "failureSummary": "Fix any of the following:\n  The main landmark is contained in another landmark."
        },
        {
          "html": "<main class=\"text t100\"><!----> <!----> <!----> <!----> <h3 style=\"--font-size-override: 1.00;\"><!----> <span>Trafikktrøbbel etter stenging av E6-tunnel</span>  <!----></h3> <!----></main>",
          "target": [
            ".hot30 > a > .t100"
          ],
          "failureSummary": "Fix any of the following:\n  The main landmark is contained in another landmark."
        },
        {
          "html": "<main class=\"text t100\"><!----> <!----> <!----> <!----> <h3><!----> <span>Spørsmålet kan gi skamfølelse. Du må slutte å stille krav til fritiden din, sier psykologen. </span>  <!----></h3> <!----></main>",
          "target": [
            ".AdWithTeaser.flipped.grid:nth-child(38) > .gridtriple.hot50.life40 > a > .t100"
          ],
          "failureSummary": "Fix any of the following:\n  The main landmark is contained in another landmark."
        },
        {
          "html": "<main class=\"text t100\"><!----> <!----> <!----> <!----> <h3 style=\"--font-size-override: 1.00;\"><!----> <span>Hørte brannalarm - fant bevisstløs mann med rykende bukse</span>  <!----></h3> <!----></main>",
          "target": [
            ".ThreeTeasers.grid:nth-child(39) > .hot60.gridtriple.life40:nth-child(1) > a > .t100"
          ],
          "failureSummary": "Fix any of the following:\n  The main landmark is contained in another landmark."
        },
        {
          "html": "<main class=\"text t100\"><!----> <!----> <!----> <!----> <h3 style=\"--font-size-override: 1.15;\"><!----> <span>Eksperter mener noe er helt endret: – Tenker på en annen måte nå</span>  <!----></h3> <!----></main>",
          "target": [
            ".ThreeTeasers.grid:nth-child(39) > .hot70.gridtriple.life40 > a > .t100"
          ],
          "failureSummary": "Fix any of the following:\n  The main landmark is contained in another landmark."
        },
        {
          "html": "<main class=\"text t100\">",
          "target": [
            ".ThreeTeasers.grid:nth-child(39) > .is-section-meninger-skin.opinion.hot60 > a > .t100"
          ],
          "failureSummary": "Fix any of the following:\n  The main landmark is contained in another landmark."
        },
        {
          "html": "<main class=\"text t100\"><!----> <!----> <!----> <!----> <h3 style=\"--font-size-override: 1.00;\"><!----> <span> Ozempic-forskeren: Prøv denne maten først</span>  <!----></h3> <!----></main>",
          "target": [
            ".AdWithTeaser.grid:nth-child(40) > .gridtriple.hot50.life40 > a > .t100"
          ],
          "failureSummary": "Fix any of the following:\n  The main landmark is contained in another landmark."
        },
        {
          "html": "<main class=\"text t100\"><!----> <!----> <!----> <!----> <h3 style=\"--font-size-override: 1.26;\"><!----> <span>Her prøver de å toppe hoppet som fikk bydelen til å riste</span>  <!----></h3> <!----></main>",
          "target": [
            ".OnePlusXTeasers.grid:nth-child(41) > .is-section-kultur-skin.gridspotlight.card-size-large > a > .t100"
          ],
          "failureSummary": "Fix any of the following:\n  The main landmark is contained in another landmark."
        },
        {
          "html": "<main class=\"text t100\"><!----> <!----> <!----> <!----> <h3 style=\"--font-size-override: 1.10;\"><!----> <span>Avslører hva som blir neste store forestilling </span>  <!----></h3> <!----></main>",
          "target": [
            ".OnePlusXTeasers.grid:nth-child(41) > .is-section-kultur-skin.hot60.is-skin:nth-child(2) > a > .t100"
          ],
          "failureSummary": "Fix any of the following:\n  The main landmark is contained in another landmark."
        },
        {
          "html": "<main class=\"text t100\">",
          "target": [
            ".is-section-ol-skin.opinion.hot60 > a > .t100"
          ],
          "failureSummary": "Fix any of the following:\n  The main landmark is contained in another landmark."
        },
        {
          "html": "<main class=\"text t100\"><!----> <!----> <!----> <!----> <h3 style=\"--font-size-override: 1.00;\"><!----> <span>Én av hundene kom tilbake etter en uke. Den andre er fortsatt savnet</span>  <!----></h3> <!----></main>",
          "target": [
            ".AdWithTeaser.flipped.grid:nth-child(42) > .gridtriple.hot50.life40 > a > .t100"
          ],
          "failureSummary": "Fix any of the following:\n  The main landmark is contained in another landmark."
        },
        {
          "html": "<main class=\"text t100\"><!----> <div class=\"labels labels-top\"><span class=\"label section TRDBY\">TRDBY</span> </div> <!----> <!----> <h3 style=\"--font-size-override: 1.00;\"><!----> <span>– Har to rom vi ikke kan bruke</span>  <!----></h3> <!----></main>",
          "target": [
            ".is-section-trdby-skin.is-skin.gridspotlightside > a > .t100"
          ],
          "failureSummary": "Fix any of the following:\n  The main landmark is contained in another landmark."
        },
        {
          "html": "<main class=\"text t100\"><!----> <!----> <!----> <!----> <h3 style=\"--font-size-override: 1.00;\"><!----> <span>– Vi ber folk om å bestille time senere</span>  <!----></h3> <!----></main>",
          "target": [
            ".flipped.OnePlusXTeasers.grid:nth-child(43) > .gridspotlight.card-size-large.hot60 > a > .t100"
          ],
          "failureSummary": "Fix any of the following:\n  The main landmark is contained in another landmark."
        },
        {
          "html": "<main class=\"text t100\"><!----> <!----> <!----> <!----> <h3 style=\"--font-size-override: 1.00;\"><!----> <span>Smak på den, dere</span>  <div grade=\"6\" class=\"grade\"><div class=\"dice\"><div></div><div></div><div></div><div></div><div></div><div></div></div></div></h3> <!----></main>",
          "target": [
            ".grade.gridspotlightside.hot50 > a > .t100"
          ],
          "failureSummary": "Fix any of the following:\n  The main landmark is contained in another landmark."
        },
        {
          "html": "<main class=\"text t100\"><!----> <div class=\"labels labels-top\"><span class=\"label section Vinter-OL\">Vinter-OL</span> </div> <!----> <!----> <h3 style=\"--font-size-override: 1.26;\"><!----> <span>Varsler OL-prat i Norge: – Jeg kommer til å ta opp dette </span>  <!----></h3> <!----></main>",
          "target": [
            ".ThreeTeasers.grid:nth-child(44) > .is-section-ol-skin.hot60.is-skin > a > .t100"
          ],
          "failureSummary": "Fix any of the following:\n  The main landmark is contained in another landmark."
        },
        {
          "html": "<main class=\"text t100\"><!----> <!----> <!----> <!----> <h3 style=\"--font-size-override: 1.00;\"><!----> <span>Ny undersøkelse om nordmenns trenings­vaner: - Resultatene overrasket oss</span>  <!----></h3> <!----></main>",
          "target": [
            ".ThreeTeasers.grid:nth-child(44) > .gridtriple.hot50.life40 > a > .t100"
          ],
          "failureSummary": "Fix any of the following:\n  The main landmark is contained in another landmark."
        },
        {
          "html": "<main class=\"text t100\"><!----> <!----> <!----> <!----> <h3 style=\"--font-size-override: 1.20;\"><!----> <span>Begynte nesten å gråte da hun  så veggene</span>  <!----></h3> <!----></main>",
          "target": [
            ".ThreeTeasers.grid:nth-child(44) > .life60.gridtriple.hot50 > a > .t100"
          ],
          "failureSummary": "Fix any of the following:\n  The main landmark is contained in another landmark."
        },
        {
          "html": "<main class=\"text t100\"><!----> <div class=\"labels labels-top\"><span class=\"label section Vinter-OL\">Vinter-OL</span> </div> <!----> <!----> <h3 style=\"--font-size-override: 1.00;\"><!----> <span>Tok til tårene etter skuffelsen:– Det er hardt</span>  <!----></h3> <!----></main>",
          "target": [
            ".hot40.is-section-ol-skin.is-skin > a > .t100"
          ],
          "failureSummary": "Fix any of the following:\n  The main landmark is contained in another landmark."
        },
        {
          "html": "<main class=\"text t100\">",
          "target": [
            ".is-section-kultur-skin.grade.gridspotlight > a > .t100"
          ],
          "failureSummary": "Fix any of the following:\n  The main landmark is contained in another landmark."
        },
        {
          "html": "<main class=\"text t100\">",
          "target": [
            ".hot40.grade.gridspotlightside > a > .t100"
          ],
          "failureSummary": "Fix any of the following:\n  The main landmark is contained in another landmark."
        },
        {
          "html": "<main class=\"text t100\"><!----> <div class=\"labels labels-top\"><span class=\"label override Kviss\">Kviss</span> </div> <!----> <!----> <h3 style=\"--font-size-override: 1.00;\"><!----> <span>Hvilke to land deler Europas lengste landegrense?</span>  <!----></h3> <!----></main>",
          "target": [
            ".OnePlusXTeasers.grid:nth-child(46) > .hot60.gridspotlightside.life40 > a > .t100"
          ],
          "failureSummary": "Fix any of the following:\n  The main landmark is contained in another landmark."
        },
        {
          "html": "<main class=\"text t100\"><!----> <!----> <!----> <!----> <h3 style=\"--font-size-override: 1.10;\"><!----> <span>– I stedet for å komme utmattet hjem, så har jeg overskudd</span>  <!----></h3> <!----></main>",
          "target": [
            ".flipped.OnePlusXTeasers.grid:nth-child(47) > .hot70.gridspotlightside.life40 > a > .t100"
          ],
          "failureSummary": "Fix any of the following:\n  The main landmark is contained in another landmark."
        },
        {
          "html": "<main class=\"text t100\"><!----> <!----> <!----> <!----> <h3 style=\"--font-size-override: 1.00;\"><!----> <span>– Dette er vanlig for meg</span>  <!----></h3> <!----></main>",
          "target": [
            ".flipped.OnePlusXTeasers.grid:nth-child(47) > .life60.gridspotlight.card-size-large > a > .t100"
          ],
          "failureSummary": "Fix any of the following:\n  The main landmark is contained in another landmark."
        },
        {
          "html": "<main class=\"text t100\">",
          "target": [
            ".hot80 > a > .t100"
          ],
          "failureSummary": "Fix any of the following:\n  The main landmark is contained in another landmark."
        },
        {
          "html": "<main class=\"text t100\"><!----> <!----> <!----> <!----> <h3 style=\"--font-size-override: 1.00;\"><!----> <span>En velfortjent vinterferie for hjernen</span>  <!----></h3> <!----></main>",
          "target": [
            ".AdWithTeaser.flipped.grid:nth-child(48) > .gridtriple.hot50.life40 > a > .t100"
          ],
          "failureSummary": "Fix any of the following:\n  The main landmark is contained in another landmark."
        },
        {
          "html": "<main class=\"text t100\"><!----> <!----> <!----> <!----> <h3><!----> <span>Har vi blitt lurt om fasting? Ny studie konluderer: Fasting hjelper lite på vektnedgang</span>  <!----></h3> <!----></main>",
          "target": [
            ".AdWithTeaser.grid:nth-child(50) > .gridtriple.hot50.life40 > a > .t100"
          ],
          "failureSummary": "Fix any of the following:\n  The main landmark is contained in another landmark."
        },
        {
          "html": "<main class=\"text t100\"><!----> <!----> <!----> <!----> <h3 style=\"--font-size-override: 1.23;\"><!----> <span> De kjøpte huset ingen andre turte å by på</span>  <!----></h3> <!----></main>",
          "target": [
            ".life60.hot60.gridtriple > a > .t100"
          ],
          "failureSummary": "Fix any of the following:\n  The main landmark is contained in another landmark."
        },
        {
          "html": "<main class=\"text t100\"><!----> <div class=\"labels labels-top\"><span class=\"label section TRDBY\">TRDBY</span> </div> <!----> <!----> <h3 style=\"--font-size-override: 1.00;\"><!----> <span>Her blir halvliteren 40 kroner billigere</span>  <!----></h3> <!----></main>",
          "target": [
            ".is-section-trdby-skin.is-skin.gridtriple > a > .t100"
          ],
          "failureSummary": "Fix any of the following:\n  The main landmark is contained in another landmark."
        },
        {
          "html": "<main class=\"text t100\"><!----> <!----> <!----> <!----> <h3 style=\"--font-size-override: 1.00;\"><!----> <span>– Oi, oi, oi</span>  <!----></h3> <!----></main>",
          "target": [
            ".ThreeTeasers.grid:nth-child(51) > .gridtriple.hot50.life40:nth-child(3) > a > .t100"
          ],
          "failureSummary": "Fix any of the following:\n  The main landmark is contained in another landmark."
        },
        {
          "html": "<main class=\"text t100\"><!----> <!----> <!----> <!----> <h3 style=\"--font-size-override: 1.00;\"><!----> <span>– I januar har det vært utrolig lite folk</span>  <!----></h3> <!----></main>",
          "target": [
            ".is-section-kultur-skin.life60.hot70 > a > .t100"
          ],
          "failureSummary": "Fix any of the following:\n  The main landmark is contained in another landmark."
        },
        {
          "html": "<main class=\"text t100\"><!----> <div class=\"labels labels-top\"><span class=\"label section MN24\">MN24</span> </div> <!----> <!----> <h3 style=\"--font-size-override: 1.00;\"><!----> <span>Kjøkkenboller tilbakekalles – avgir kreftfremkallende stoff</span>  <!----></h3> <!----></main>",
          "target": [
            ".is-section-mn24-skin.life60.is-skin > a > .t100"
          ],
          "failureSummary": "Fix any of the following:\n  The main landmark is contained in another landmark."
        },
        {
          "html": "<main class=\"text t100\"><!----> <!----> <!----> <!----> <h3 style=\"--font-size-override: 1.00;\"><!----> <span>Småbarnsfar frifunnet etter å ha kjørt 120 km/t i 50-sone</span>  <!----></h3> <!----></main>",
          "target": [
            ".OnePlusXTeasers.grid:nth-child(52) > .life60.gridspotlightside.hot50:nth-child(3) > a > .t100"
          ],
          "failureSummary": "Fix any of the following:\n  The main landmark is contained in another landmark."
        },
        {
          "html": "<main class=\"text t100\"><!----> <!----> <!----> <!----> <h3 style=\"--font-size-override: 1.00;\"><!----> <span>– Jeg blir sur av kjæreste-spørsmålene</span>  <!----></h3> <!----></main>",
          "target": [
            ".AdWithTeaser.flipped.grid:nth-child(53) > .hot60.gridtriple.life40 > a > .t100"
          ],
          "failureSummary": "Fix any of the following:\n  The main landmark is contained in another landmark."
        },
        {
          "html": "<main class=\"text t100\"><!----> <!----> <!----> <!----> <h3 style=\"--font-size-override: 1.00;\"><!----> <span> En enkel, god og rask middagsrett</span>  <!----></h3> <!----></main>",
          "target": [
            ".flipped.OnePlusXTeasers.grid:nth-child(54) > .gridspotlightside.hot50.life40 > a > .t100"
          ],
          "failureSummary": "Fix any of the following:\n  The main landmark is contained in another landmark."
        },
        {
          "html": "<main class=\"text t100\"><!----> <div class=\"labels labels-top\"><span class=\"label override Høiby-saken\">Høiby-saken</span> </div> <!----> <!----> <h3 style=\"--font-size-override: 1.55;\"><!----> <span>– Hadde lyst til å redde ham</span>  <!----></h3> <!----></main>",
          "target": [
            ".flipped.OnePlusXTeasers.grid:nth-child(54) > .life60.gridspotlight.card-size-large > a > .t100"
          ],
          "failureSummary": "Fix any of the following:\n  The main landmark is contained in another landmark."
        },
        {
          "html": "<main class=\"text t100\"><!----> <!----> <!----> <!----> <h3 style=\"--font-size-override: 1.00;\"><!----> <span>Vil du gi barna god selvfølelse? Start med deg selv, råder pedagogen</span>  <!----></h3> <!----></main>",
          "target": [
            ".flipped.OnePlusXTeasers.grid:nth-child(54) > .life60.gridspotlightside.hot50 > a > .t100"
          ],
          "failureSummary": "Fix any of the following:\n  The main landmark is contained in another landmark."
        },
        {
          "html": "<main class=\"text t100\"><!----> <!----> <!----> <!----> <h3 style=\"--font-size-override: 0.95;\"><!----> <span>Lege og tidligere eliteløper: - Dette er den største feilen mosjonister gjør</span>  <!----></h3> <!----></main>",
          "target": [
            ".gridtriple.hot50.life40:nth-child(1) > a > .t100"
          ],
          "failureSummary": "Fix any of the following:\n  The main landmark is contained in another landmark."
        },
        {
          "html": "<main class=\"text t100\"><!----> <!----> <!----> <!----> <h3 style=\"--font-size-override: 1.00;\"><span class=\"prefix\">Se kortfilmen: </span> <span>Frittgående</span>  <!----></h3> <!----></main>",
          "target": [
            ".ThreeTeasers.grid:nth-child(55) > .hot60.gridtriple.life40 > a > .t100"
          ],
          "failureSummary": "Fix any of the following:\n  The main landmark is contained in another landmark."
        },
        {
          "html": "<main class=\"text t100\"><!----> <!----> <!----> <!----> <h3><!----> <span>Han har forsket på hjernen i over 30 år. Spesielt tre matvarer vil han spise mer av i 2026.</span>  <!----></h3> <!----></main>",
          "target": [
            ".ThreeTeasers.grid:nth-child(55) > .gridtriple.hot50.life40:nth-child(3) > a > .t100"
          ],
          "failureSummary": "Fix any of the following:\n  The main landmark is contained in another landmark."
        }
      ]
    },
    {
      "id": "landmark-no-duplicate-main",
      "impact": "moderate",
      "description": "Ensure the document has at most one main landmark",
      "help": "Document should not have more than one main landmark",
      "helpUrl": "https://dequeuniversity.com/rules/axe/4.11/landmark-no-duplicate-main?application=playwright",
      "tags": [
        "cat.semantics",
        "best-practice"
      ],
      "violation_count": 1,
      "nodes": [
        {
          "html": "<main class=\"Layout\">",
          "target": [
            ".Layout"
          ],
          "failureSummary": "Fix any of the following:\n  Document has more than one main landmark"
        }
      ]
    },
    {
      "id": "landmark-unique",
      "impact": "moderate",
      "description": "Ensure landmarks are unique",
      "help": "Landmarks should have a unique role or role/label/title (i.e. accessible name) combination",
      "helpUrl": "https://dequeuniversity.com/rules/axe/4.11/landmark-unique?application=playwright",
      "tags": [
        "cat.semantics",
        "best-practice"
      ],
      "violation_count": 2,
      "nodes": [
        {
          "html": "<aside class=\"gdpr-wrapper top\">",
          "target": [
            ".top"
          ],
          "failureSummary": "Fix any of the following:\n  The landmark must have a unique aria-label, aria-labelledby, or title to make landmarks distinguishable"
        },
        {
          "html": "<main class=\"Layout\">",
          "target": [
            ".Layout"
          ],
          "failureSummary": "Fix any of the following:\n  The landmark must have a unique aria-label, aria-labelledby, or title to make landmarks distinguishable"
        }
      ]
    },
    {
      "id": "link-in-text-block",
      "impact": "serious",
      "description": "Ensure links are distinguished from surrounding text in a way that does not rely on color",
      "help": "Links must be distinguishable without relying on color",
      "helpUrl": "https://dequeuniversity.com/rules/axe/4.11/link-in-text-block?application=playwright",
      "tags": [
        "cat.color",
        "wcag2a",
        "wcag141",
        "TTv5",
        "TT13.a",
        "EN-301-549",
        "EN-9.1.4.1",
        "RGAAv4",
        "RGAA-10.6.1"
      ],
      "violation_count": 6,
      "nodes": [
        {
          "html": "<a href=\"https://adresseavisen.e-pages.pub/\">eAdressa</a>",
          "target": [
            "a:nth-child(5)"
          ],
          "failureSummary": "Fix any of the following:\n  The link has insufficient color contrast of 2.49:1 with the surrounding text. (Minimum contrast is 3:1, link text: #005379, surrounding text: #010101)\n  The link has no styling (such as underline) to distinguish it from the surrounding text"
        },
        {
          "html": "<a href=\"tel:46407200\">464 07200</a>",
          "target": [
            "section:nth-child(4) > div > div > .Tips > dl > dd > a[href=\"tel:46407200\"]"
          ],
          "failureSummary": "Fix any of the following:\n  The link has insufficient color contrast of 2.49:1 with the surrounding text. (Minimum contrast is 3:1, link text: #005379, surrounding text: #010101)\n  The link has no styling (such as underline) to distinguish it from the surrounding text"
        },
        {
          "html": "<a href=\"https://presse.no/pfu/etiske-regler/vaer-varsom-plakaten/\">Vær Varsom-plakatens</a>",
          "target": [
            "div > div > p > a:nth-child(1)"
          ],
          "failureSummary": "Fix any of the following:\n  The link has insufficient color contrast of 2.49:1 with the surrounding text. (Minimum contrast is 3:1, link text: #005379, surrounding text: #010101)\n  The link has no styling (such as underline) to distinguish it from the surrounding text"
        },
        {
          "html": "<a href=\"https://www.redaktor.no/ressurser/etiske-og-juridiske-rammeverk/redaktorplakaten\">Redaktøransvar</a>",
          "target": [
            "p > a:nth-child(2)"
          ],
          "failureSummary": "Fix any of the following:\n  The link has insufficient color contrast of 2.49:1 with the surrounding text. (Minimum contrast is 3:1, link text: #005379, surrounding text: #010101)\n  The link has no styling (such as underline) to distinguish it from the surrounding text"
        },
        {
          "html": "<a href=\"https://www.medietilsynet.no/\">Medietilsynet</a>",
          "target": [
            "a[href$=\"medietilsynet.no/\"]"
          ],
          "failureSummary": "Fix any of the following:\n  The link has insufficient color contrast of 2.49:1 with the surrounding text. (Minimum contrast is 3:1, link text: #005379, surrounding text: #010101)\n  The link has no styling (such as underline) to distinguish it from the surrounding text"
        },
        {
          "html": "<a href=\"https://www.adressa.no/nyheter/i/lVOBge/adresseavisens-rettigheter\">Adresseavisens rettigheter.</a>",
          "target": [
            "p > a:nth-child(4)"
          ],
          "failureSummary": "Fix any of the following:\n  The link has insufficient color contrast of 2.49:1 with the surrounding text. (Minimum contrast is 3:1, link text: #005379, surrounding text: #010101)\n  The link has no styling (such as underline) to distinguish it from the surrounding text"
        }
      ]
    },
    {
      "id": "tabindex",
      "impact": "serious",
      "description": "Ensure tabindex attribute values are not greater than 0",
      "help": "Elements should not have tabindex greater than zero",
      "helpUrl": "https://dequeuniversity.com/rules/axe/4.11/tabindex?application=playwright",
      "tags": [
        "cat.keyboard",
        "best-practice"
      ],
      "violation_count": 2,
      "nodes": [
        {
          "html": "<button tabindex=\"1\" aria-controls=\"usermenu\" aria-expanded=\"false\" aria-label=\"Brukermeny\" class=\"user menu-icon\"><span class=\"user-initials\"></span> <span class=\"notification-count\" style=\"display:none;\">0</span></button>",
          "target": [
            ".user"
          ],
          "failureSummary": "Fix any of the following:\n  Element has a tabindex greater than 0"
        },
        {
          "html": "<button tabindex=\"1\" aria-controls=\"submenu\" aria-expanded=\"false\" aria-label=\"Åpne- og lukkeknapp for meny\" class=\"menu-icon main\"><span></span></button>",
          "target": [
            ".main"
          ],
          "failureSummary": "Fix any of the following:\n  Element has a tabindex greater than 0"
        }
      ]
    }
  ]
}